show_image.py
show_image-0.0.1.dist-info/METADATA
show_image-0.0.1.dist-info/WHEEL
show_image-0.0.1.dist-info/top_level.txt
show_image-0.0.1.dist-info/RECORD
