Metadata-Version: 2.1
Name: show-image
Version: 0.0.1
Summary: Display image in internactive notebooks
Home-page: https://github.com/adynathos/ipy_show_image
Author: Adynathos
Author-email: adynathos@protonmail.com
License: MIT
Platform: UNKNOWN
Classifier: Programming Language :: Python :: 3
Classifier: License :: OSI Approved :: MIT License
Classifier: Operating System :: OS Independent
Requires-Python: >=3.6
Requires-Dist: pillow (>=5.3.0)
Requires-Dist: numpy (>=1.17.0)
Requires-Dist: ipython (>=7.0.0)
Requires-Dist: matplotlib (>=3.0.0)
